Metadata-Version: 2.1
Name: Rmath
Version: 3.4.1
Summary: standalone Rmath library from R
Home-page: https://github.com/ntessore/Rmath-python
Author: Nicolas Tessore
Author-email: n.tessore@ucl.ac.uk
License: UNKNOWN
Platform: UNKNOWN
Classifier: Programming Language :: Python :: 3
Classifier: License :: OSI Approved :: GNU General Public License v2 (GPLv2)
Classifier: Operating System :: OS Independent
